BPMtoFPS/__init__.py
BPMtoFPS/main.py
BPMtoFPS/setup.py
BPMtoFPS-1.4.0.dist-info/LICENSE
BPMtoFPS-1.4.0.dist-info/METADATA
BPMtoFPS-1.4.0.dist-info/WHEEL
BPMtoFPS-1.4.0.dist-info/top_level.txt
BPMtoFPS-1.4.0.dist-info/RECORD
