Metadata-Version: 2.1
Name: BPMtoFPS
Version: 1.4.0
Summary: Convert time in a musical composition to time in a video production.
Author-email: "Jeff Heller (JHGFD)" <jeffheller@jhgfd.com>
Project-URL: Homepage, https://github.com/JHGFD82/BPMtoFPS
Project-URL: Issues, https://github.com/JHGFD82/BPMtoFPS/issues
Classifier: Programming Language :: Python :: 3.6
Classifier: License :: OSI Approved :: GNU General Public License v3 (GPLv3)
Classifier: Operating System :: OS Independent
Classifier: Topic :: Multimedia :: Sound/Audio
Classifier: Topic :: Multimedia :: Video
Requires-Python: >=3.6
License-File: LICENSE
